dicom_image_tools/__init__.py
dicom_image_tools/constants/SopClassUids.py
dicom_image_tools/constants/__init__.py
dicom_image_tools/constants/plotting.py
dicom_image_tools/ct_tools/__init__.py
dicom_image_tools/ct_tools/patient_equivalent_diameter.py
dicom_image_tools/dicom_handlers/__init__.py
dicom_image_tools/dicom_handlers/ct.py
dicom_image_tools/dicom_handlers/dicom_import.py
dicom_image_tools/dicom_handlers/dicom_series.py
dicom_image_tools/dicom_handlers/dicom_study.py
dicom_image_tools/dicom_handlers/dose_matrix.py
dicom_image_tools/dicom_handlers/dose_report_class.py
dicom_image_tools/dicom_handlers/projection.py
dicom_image_tools/dicom_handlers/save_dicom.py
dicom_image_tools/helpers/__init__.py
dicom_image_tools/helpers/check_path_is_valid.py
dicom_image_tools/helpers/geometry.py
dicom_image_tools/helpers/normalize_dicom_exposure_parameters.py
dicom_image_tools/helpers/patient_centering.py
dicom_image_tools/helpers/pixel_data.py
dicom_image_tools/helpers/point.py
dicom_image_tools/helpers/remove_position_indication_square.py
dicom_image_tools/helpers/rotate_image.py
dicom_image_tools/helpers/voxel_data.py
dicom_image_tools/helpers/window.py
dicom_image_tools/image_quality/__init__.py
dicom_image_tools/image_quality/lcd.py
dicom_image_tools/image_quality/mtf.py
dicom_image_tools/image_quality/variance_image.py
dicom_image_tools/plotting/__init__.py
dicom_image_tools/plotting/colour_scales.py
dicom_image_tools/plotting/plotly.py
dicom_image_tools/roi/__init__.py
dicom_image_tools/roi/roi.py
dicom_image_tools/roi/square_roi.py
dicom_image_tools-25.0.0.dist-info/licenses/LICENSE.txt
dicom_image_tools-25.0.0.dist-info/METADATA
dicom_image_tools-25.0.0.dist-info/WHEEL
dicom_image_tools-25.0.0.dist-info/top_level.txt
dicom_image_tools-25.0.0.dist-info/RECORD
