Metadata-Version: 2.4
Name: dicom_image_tools
Version: 25.0.0
Summary: Python package for managing DICOM images from different modalities
Author-email: Josef Lundman <josef@lundman.eu>
Maintainer-email: Josef Lundman <josef@lundman.eu>
License-Expression: MIT
Project-URL: Homepage, https://github.com/BwKodex/dicomimagetools
Project-URL: Repository, https://github.com/BwKodex/dicomimagetools
Classifier: Intended Audience :: Developers
Classifier: Development Status :: 5 - Production/Stable
Classifier: Programming Language :: Python :: 3
Requires-Python: >=3.11
License-File: LICENSE.txt
Requires-Dist: pydicom>=2.3.1
Requires-Dist: numpy>=2.0.0
Requires-Dist: scikit-image>=0.17.2
Requires-Dist: scipy>=1.9.3
Requires-Dist: plotly>=5.11.0
Requires-Dist: python-gdcm>=3.0.20
Dynamic: license-file
